LICENSE
vault_management_api_client/__init__.py
vault_management_api_client/api/__init__.py
vault_management_api_client/api/attachments_fields/__init__.py
vault_management_api_client/api/attachments_fields/delete_object_attachment_id.py
vault_management_api_client/api/attachments_fields/get_object_attachment_id.py
vault_management_api_client/api/attachments_fields/get_object_exposed_id.py
vault_management_api_client/api/attachments_fields/get_object_notes_id.py
vault_management_api_client/api/attachments_fields/get_object_password_id.py
vault_management_api_client/api/attachments_fields/get_object_totp_id.py
vault_management_api_client/api/attachments_fields/get_object_uri_id.py
vault_management_api_client/api/attachments_fields/get_object_username_id.py
vault_management_api_client/api/attachments_fields/post_attachment.py
vault_management_api_client/api/collections_organizations/__init__.py
vault_management_api_client/api/collections_organizations/delete_object_org_collection_id.py
vault_management_api_client/api/collections_organizations/get_list_object_collections.py
vault_management_api_client/api/collections_organizations/get_list_object_org_collections.py
vault_management_api_client/api/collections_organizations/get_list_object_org_members.py
vault_management_api_client/api/collections_organizations/get_list_object_organizations.py
vault_management_api_client/api/collections_organizations/get_object_org_collection_id.py
vault_management_api_client/api/collections_organizations/post_confirm_org_member_id.py
vault_management_api_client/api/collections_organizations/post_move_itemid_organization_id.py
vault_management_api_client/api/collections_organizations/post_object_org_collection.py
vault_management_api_client/api/collections_organizations/put_object_org_collection_id.py
vault_management_api_client/api/folders/__init__.py
vault_management_api_client/api/folders/delete_object_folder_id.py
vault_management_api_client/api/folders/get_list_object_folders.py
py_bw_vault_management_api_client-0.18.dist-info/LICENSE
py_bw_vault_management_api_client-0.18.dist-info/METADATA
py_bw_vault_management_api_client-0.18.dist-info/WHEEL
py_bw_vault_management_api_client-0.18.dist-info/RECORD
