Metadata-Version: 2.1
Name: py-bw-vault-management-api-client
Version: 0.18
Summary: Unofficial client library for accessing the BitWarden Vault Management API
Requires-Python: >=3.9,<4.0
Classifier: Development Status :: 3 - Alpha
Classifier: Intended Audience :: Developers
Classifier: License :: OSI Approved :: GNU Lesser General Public License v2 or later (LGPLv2+)
Classifier: Programming Language :: Python :: 3
Classifier: Programming Language :: Python :: 3.9
Classifier: Programming Language :: Python :: 3.10
Classifier: Programming Language :: Python :: 3.11
Classifier: Programming Language :: Python :: 3.12
Classifier: Programming Language :: Python :: 3.13
Requires-Dist: attrs (>=22.2.0)
Requires-Dist: httpx (>=0.20.0,<0.29.0)
Requires-Dist: python-dateutil (>=2.8.0,<3.0.0)
